[
    {
        "href":"afshoreh.webp",
        "color":"#f1f2f3"
    },
    {
        "href":"akbarjojo.webp",
        "color":"#d71920"
    },
    {
        "href":"alomorq.webp",
        "color":"#f1f2f3"
    },
    {
        "href":"alpomo.webp",
        "color":"#f1f2f3"
    },
    {
        "href":"barkhordari.webp",
        "color":"#2f446a"
    },
    {
        "href":"caspian.webp",
        "color":"#2f446a"
    },
    {
        "href":"chuckles.webp",
        "color":"#f1f2f3"
    },
    {
        "href":"graph.webp",
        "color":"#f1f2f3"
    },
    {
        "href":"green.webp",
        "color":"#f1f2f3"
    },
    {
        "href":"ir.webp",
        "color":"#e1e2e3"
    },
    {
        "href":"jazmobl.webp",
        "color":"#e1e2e3"
    },
    {
        "href":"mahdavi.webp",
        "color":"#e1e2e3"
    },
    {
        "href":"mana.webp",
        "color":"#e1e2e3"
    },
    {
        "href":"mazmelk.webp",
        "color":"#e1e2e3"
    },
    {
        "href":"parnazt.webp",
        "color":"#e1e2e3"
    },
    {
        "href":"parsins.webp",
        "color":"#e1e2e3"
    },
    {
        "href":"pordarom.webp",
        "color":"#e1e2e3"
    },
    {
        "href":"razimed.webp",
        "color":"#e1e2e3"
    },
    {
        "href":"royalhome.webp",
        "color":"#e1e2e3"
    },
    {
        "href":"sepehrlift.webp",
        "color":"#e1e2e3"
    },
    {
        "href":"snowa.webp",
        "color":"#e1e2e3"
    },
    {
        "href":"station.webp",
        "color":"#e1e2e3"
    }    
]